sdn_cli.py
lib/__init__.py
lib/flask_app.py
lib/noia_speedtest.py
lib/sdn_client.py
lib/sdn_pinger.py
lib/sdn_speedtest.py
lib/traceroute.py
noia_inspector-0.3.39.data/data/noia-inspector/default.env
noia_inspector-0.3.39.data/data/noia-inspector/destinations.json
settings/__init__.py
noia_inspector-0.3.39.dist-info/METADATA
noia_inspector-0.3.39.dist-info/WHEEL
noia_inspector-0.3.39.dist-info/entry_points.txt
noia_inspector-0.3.39.dist-info/top_level.txt
noia_inspector-0.3.39.dist-info/RECORD
